[
  {
    "text": "nopeee",
    "intent": "deny",
    "intent_prediction": {
      "name": "inform_person",
      "confidence": 0.44670083819942885
    }
  },
  {
    "text": "Correct",
    "intent": "inform_action",
    "intent_prediction": {
      "name": "affirm",
      "confidence": 0.439468167496223
    }
  },
  {
    "text": "Nullish",
    "intent": "inform_action",
    "intent_prediction": {
      "name": "inform_person",
      "confidence": 0.44670083819942885
    }
  },
  {
    "text": "Unpublish",
    "intent": "inform_action",
    "intent_prediction": {
      "name": "inform_person",
      "confidence": 0.44670083819942885
    }
  }
]